cache_to_disk/__init__.py
cache_to_disk/cache_to_disk.py
cache_to_disk-2.0.0.dist-info/LICENSE
cache_to_disk-2.0.0.dist-info/METADATA
cache_to_disk-2.0.0.dist-info/WHEEL
cache_to_disk-2.0.0.dist-info/top_level.txt
cache_to_disk-2.0.0.dist-info/RECORD
