Metadata-Version: 2.1
Name: cache_to_disk
Version: 2.0.0
Summary: Local disk caching decorator for python function.
Home-page: https://github.com/sarenehan/cache_to_disk
Author: Stewart Renehan
Author-email: sarenehan@gmail.com
License: UNKNOWN
Platform: UNKNOWN
Classifier: Programming Language :: Python :: 3
Classifier: License :: OSI Approved :: MIT License
Classifier: Operating System :: OS Independent
